pytest_testdirectory/__init__.py
pytest_testdirectory/checkoutput.py
pytest_testdirectory/runresult.py
pytest_testdirectory/runresulterror.py
pytest_testdirectory/testdirectory.py
pytest_testdirectory-5.0.0.dist-info/LICENSE.rst
pytest_testdirectory-5.0.0.dist-info/METADATA
pytest_testdirectory-5.0.0.dist-info/WHEEL
pytest_testdirectory-5.0.0.dist-info/entry_points.txt
pytest_testdirectory-5.0.0.dist-info/top_level.txt
pytest_testdirectory-5.0.0.dist-info/RECORD
