Metadata-Version: 2.1
Name: pytest-testdirectory
Version: 5.0.0
Summary: A py.test plugin providing temporary directories in unit tests.
Home-page: https://github.com/steinwurf/pytest-testdirectory
Author: Steinwurf ApS
Author-email: contact@steinwurf.com
License: BSD 3-clause "New" or "Revised" License
Keywords: pytest py.test testing unit tests plugin
Platform: UNKNOWN
Classifier: Framework :: Pytest
Classifier: Development Status :: 5 - Production/Stable
Classifier: Environment :: Plugins
Classifier: Intended Audience :: Developers
Classifier: License :: OSI Approved :: BSD License
Classifier: Operating System :: OS Independent
Classifier: Programming Language :: Python
Classifier: Topic :: Software Development :: Testing
License-File: LICENSE.rst
Requires-Dist: pytest
